[
    {
        "id": 146381379,
        "name": "cờ ô ăn quan 6 trong 1 .5 trong 1",
        "url_key": "co-o-an-quan-6-trong-1-5-trong-1-p146381379",
        "price": 93500,
        "description": "MÔ TẢ SẢN PHẨM - Cờ Ô Quan thiết kế thông minh bao gồm 6 trò chơi dân gian, đưa trẻ nhỏ về với những trò chơi truyền thống quen thuộc. Sản phẩm giúp trẻ định hình về tư duy logic đơn giản và phân biệt cơ bản về các trò chơi dân gian. - Có 6 loại cờ: Ô quan, Cờ vây, Cờ caro, Cờ cá ngựa, Cờ nhảy, Cờ gánh. * Quân cờ nhảy: 30 quân loại nhỏ. * Quân cờ Cá Ngựa: 16 quân loại lớn. * Quân cờ Ô quan, Caro, Gánh, Vây: 81 quân và 2 Quan. Thông tin sản phẩm: * Có 6 loại cờ: Ô quan – Vây – Caro – Cá ngựa – Nhảy – Gánh. * Quân cờ nhảy: 30 quân loại nhỏ. * Quân cờ Cá Ngựa: 16 quân loại lớn. * Quân cờ Ô quan – Caro – Gánh – Vây: 81 quân và 2 Quan. * Diện tích bàn: 760mm x 255mm * Thành phần: Quân cờ - Xúc xắc: Nhựa * Bàn cờ: Giấy * Hộp cờ: Giấy. * Sản xuất : Việt Nam Giá sản phẩm trên Tiki đã bao gồm thuế theo luật hiện hành. Bên cạnh đó, tuỳ vào loại sản phẩm, hình thức và địa chỉ giao hàng mà có thể phát sinh thêm chi phí khác như phí vận chuyển, phụ phí hàng cồng kềnh, thuế nhập khẩu (đối với đơn hàng giao từ nước ngoài có giá trị trên 1 triệu đồng).....",
        "images": [
            {
                "base_url": "https://salt.tikicdn.com/ts/product/3e/b0/8d/91990594d1630abdaafa2bd50000c92b.jpg",
                "is_gallery": true,
                "label": null,
                "large_url": "https://salt.tikicdn.com/cache/w1200/ts/product/3e/b0/8d/91990594d1630abdaafa2bd50000c92b.jpg",
                "medium_url": "https://salt.tikicdn.com/cache/w300/ts/product/3e/b0/8d/91990594d1630abdaafa2bd50000c92b.jpg",
                "position": null,
                "small_url": "https://salt.tikicdn.com/cache/200x280/ts/product/3e/b0/8d/91990594d1630abdaafa2bd50000c92b.jpg",
                "thumbnail_url": "https://salt.tikicdn.com/cache/200x280/ts/product/3e/b0/8d/91990594d1630abdaafa2bd50000c92b.jpg"
            },
            {
                "base_url": "https://salt.tikicdn.com/ts/product/a0/45/79/932eff06485518734b62b36aa82ae949.jpg",
                "is_gallery": true,
                "label": null,
                "large_url": "https://salt.tikicdn.com/cache/w1200/ts/product/a0/45/79/932eff06485518734b62b36aa82ae949.jpg",
                "medium_url": "https://salt.tikicdn.com/cache/w300/ts/product/a0/45/79/932eff06485518734b62b36aa82ae949.jpg",
                "position": null,
                "small_url": "https://salt.tikicdn.com/cache/200x280/ts/product/a0/45/79/932eff06485518734b62b36aa82ae949.jpg",
                "thumbnail_url": "https://salt.tikicdn.com/cache/200x280/ts/product/a0/45/79/932eff06485518734b62b36aa82ae949.jpg"
            },
            {
                "base_url": "https://salt.tikicdn.com/ts/product/a7/0e/2f/ffd96de88263eb7ef3bdeab60f6b2d1b.jpg",
                "is_gallery": true,
                "label": null,
                "large_url": "https://salt.tikicdn.com/cache/w1200/ts/product/a7/0e/2f/ffd96de88263eb7ef3bdeab60f6b2d1b.jpg",
                "medium_url": "https://salt.tikicdn.com/cache/w300/ts/product/a7/0e/2f/ffd96de88263eb7ef3bdeab60f6b2d1b.jpg",
                "position": null,
                "small_url": "https://salt.tikicdn.com/cache/200x280/ts/product/a7/0e/2f/ffd96de88263eb7ef3bdeab60f6b2d1b.jpg",
                "thumbnail_url": "https://salt.tikicdn.com/cache/200x280/ts/product/a7/0e/2f/ffd96de88263eb7ef3bdeab60f6b2d1b.jpg"
            },
            {
                "base_url": "https://salt.tikicdn.com/ts/product/de/16/64/9ef009e33e817137638368d0eb184680.jpg",
                "is_gallery": true,
                "label": null,
                "large_url": "https://salt.tikicdn.com/cache/w1200/ts/product/de/16/64/9ef009e33e817137638368d0eb184680.jpg",
                "medium_url": "https://salt.tikicdn.com/cache/w300/ts/product/de/16/64/9ef009e33e817137638368d0eb184680.jpg",
                "position": null,
                "small_url": "https://salt.tikicdn.com/cache/200x280/ts/product/de/16/64/9ef009e33e817137638368d0eb184680.jpg",
                "thumbnail_url": "https://salt.tikicdn.com/cache/200x280/ts/product/de/16/64/9ef009e33e817137638368d0eb184680.jpg"
            },
            {
                "base_url": "https://salt.tikicdn.com/ts/product/a0/62/3e/b4b32e6aaddff5654df69f261bd26fc1.jpg",
                "is_gallery": true,
                "label": null,
                "large_url": "https://salt.tikicdn.com/cache/w1200/ts/product/a0/62/3e/b4b32e6aaddff5654df69f261bd26fc1.jpg",
                "medium_url": "https://salt.tikicdn.com/cache/w300/ts/product/a0/62/3e/b4b32e6aaddff5654df69f261bd26fc1.jpg",
                "position": null,
                "small_url": "https://salt.tikicdn.com/cache/200x280/ts/product/a0/62/3e/b4b32e6aaddff5654df69f261bd26fc1.jpg",
                "thumbnail_url": "https://salt.tikicdn.com/cache/200x280/ts/product/a0/62/3e/b4b32e6aaddff5654df69f261bd26fc1.jpg"
            }
        ]
    },
    {
        "id": 755473,
        "name": "Cờ Ô Quan Hộp Giấy Lớn Liên Hiệp Thành KOQHGL",
        "url_key": "co-o-quan-hop-giay-lon-lien-hiep-thanh-koqhgl-p755473",
        "price": 114000,
        "description": "Cờ Ô Quan Hộp Giấy Lớn KOQHGL thiết kế thông minh bao gồm 6 trò chơi dân gian, đưa trẻ nhỏ về với những trò chơi truyền thống quen thuộc. Sản phẩm giúp trẻ định hình về tư duy logic đơn giản và phân biệt cơ bản về các trò chơi dân gian. Luật chơi đơn giản, dễ chơi, bé có thể chơi cùng với ba mẹ và bạn bè. Có 6 loại cờ: Ô quan, Cờ vây, Cờ caro, Cờ cá ngựa, Cờ nhảy, Cờ gánh. Quân cờ nhảy: 30 quân loại nhỏ. Quân cờ Cá Ngựa: 16 quân loại lớn. Quân cờ Ô quan, Caro, Gánh, Vây: 81 quân và 2 Quan. Diện tích bàn cờ: 760mm x 255mm Giá sản phẩm trên Tiki đã bao gồm thuế theo luật hiện hành. Bên cạnh đó, tuỳ vào loại sản phẩm, hình thức và địa chỉ giao hàng mà có thể phát sinh thêm chi phí khác như phí vận chuyển, phụ phí hàng cồng kềnh, thuế nhập khẩu (đối với đơn hàng giao từ nước ngoài có giá trị trên 1 triệu đồng).....",
        "images": [
            {
                "base_url": "https://salt.tikicdn.com/media/catalog/product/1/_/1.u5430.d20170728.t180646.934747.jpg",
                "is_gallery": true,
                "label": null,
                "large_url": "https://salt.tikicdn.com/cache/w1200/media/catalog/product/1/_/1.u5430.d20170728.t180646.934747.jpg",
                "medium_url": "https://salt.tikicdn.com/cache/w300/media/catalog/product/1/_/1.u5430.d20170728.t180646.934747.jpg",
                "position": null,
                "small_url": "https://salt.tikicdn.com/cache/200x280/media/catalog/product/1/_/1.u5430.d20170728.t180646.934747.jpg",
                "thumbnail_url": "https://salt.tikicdn.com/cache/200x280/media/catalog/product/1/_/1.u5430.d20170728.t180646.934747.jpg"
            },
            {
                "base_url": "https://salt.tikicdn.com/media/catalog/product/2/_/2.u5430.d20170728.t180646.978577.jpg",
                "is_gallery": true,
                "label": null,
                "large_url": "https://salt.tikicdn.com/cache/w1200/media/catalog/product/2/_/2.u5430.d20170728.t180646.978577.jpg",
                "medium_url": "https://salt.tikicdn.com/cache/w300/media/catalog/product/2/_/2.u5430.d20170728.t180646.978577.jpg",
                "position": null,
                "small_url": "https://salt.tikicdn.com/cache/200x280/media/catalog/product/2/_/2.u5430.d20170728.t180646.978577.jpg",
                "thumbnail_url": "https://salt.tikicdn.com/cache/200x280/media/catalog/product/2/_/2.u5430.d20170728.t180646.978577.jpg"
            },
            {
                "base_url": "https://salt.tikicdn.com/media/catalog/product/3/_/3.u5430.d20170728.t180647.16953.jpg",
                "is_gallery": true,
                "label": null,
                "large_url": "https://salt.tikicdn.com/cache/w1200/media/catalog/product/3/_/3.u5430.d20170728.t180647.16953.jpg",
                "medium_url": "https://salt.tikicdn.com/cache/w300/media/catalog/product/3/_/3.u5430.d20170728.t180647.16953.jpg",
                "position": null,
                "small_url": "https://salt.tikicdn.com/cache/200x280/media/catalog/product/3/_/3.u5430.d20170728.t180647.16953.jpg",
                "thumbnail_url": "https://salt.tikicdn.com/cache/200x280/media/catalog/product/3/_/3.u5430.d20170728.t180647.16953.jpg"
            },
            {
                "base_url": "https://salt.tikicdn.com/media/catalog/product/4/_/4.u5430.d20170728.t180647.53830.jpg",
                "is_gallery": true,
                "label": null,
                "large_url": "https://salt.tikicdn.com/cache/w1200/media/catalog/product/4/_/4.u5430.d20170728.t180647.53830.jpg",
                "medium_url": "https://salt.tikicdn.com/cache/w300/media/catalog/product/4/_/4.u5430.d20170728.t180647.53830.jpg",
                "position": null,
                "small_url": "https://salt.tikicdn.com/cache/200x280/media/catalog/product/4/_/4.u5430.d20170728.t180647.53830.jpg",
                "thumbnail_url": "https://salt.tikicdn.com/cache/200x280/media/catalog/product/4/_/4.u5430.d20170728.t180647.53830.jpg"
            }
        ]
    }
]